composition_entity_linker/__init__.py
composition_entity_linker/linker.py
composition_entity_linker/track.py
composition_entity_linker/utils.py
composition_entity_linker/ref_corpus/CEL_meta_new.csv
composition_entity_linker/ref_corpus/composer_translations.json
composition_entity_linker/ref_corpus/openopus_corpus.json
composition_entity_linker-0.0.6.dist-info/METADATA
composition_entity_linker-0.0.6.dist-info/WHEEL
composition_entity_linker-0.0.6.dist-info/licenses/LICENSE
composition_entity_linker-0.0.6.dist-info/RECORD
