Metadata-Version: 2.1
Name: composition_entity_linker
Version: 0.0.6
Summary: Tool for linking classical music record & track to the corresponding composition / movement. 
Project-URL: Homepage, https://github.com/anusfoil/Composition-Entity-Linker
Project-URL: Bug Tracker, https://github.com/anusfoil/Composition-Entity-Linker/issues
Author-email: Huan Zhang <huan.zhang@qmul.ac.uk>, Jingjing Tang <jingjing.tang@qmul.ac.uk>
License: Copyright (c) 2018 The Python Packaging Authority
Classifier: License :: OSI Approved :: MIT License
Classifier: Operating System :: OS Independent
Classifier: Programming Language :: Python :: 3
Requires-Python: >=3.7
